.DS_Store
backstepping_controller/__init__.py
backstepping_controller/controller.py
backstepping_controller/plotting.py
backstepping_controller/saving.py
backstepping_controller/simulation.py
backstepping_controller/test.py
backstepping_controller-0.1.3.dist-info/METADATA
backstepping_controller-0.1.3.dist-info/WHEEL
backstepping_controller-0.1.3.dist-info/top_level.txt
backstepping_controller-0.1.3.dist-info/RECORD
